aw/__init__.py
aw/__main__.py
aw/auth.py
aw/cmd.py
aw/exceptions.py
aw/init.py
aw/io.py
aw/parse.py
aw/tools.py
awftp-1.1.0.dist-info/DESCRIPTION.rst
awftp-1.1.0.dist-info/METADATA
awftp-1.1.0.dist-info/RECORD
awftp-1.1.0.dist-info/WHEEL
awftp-1.1.0.dist-info/entry_points.txt
awftp-1.1.0.dist-info/metadata.json
awftp-1.1.0.dist-info/top_level.txt
version/__init__.py
