Metadata-Version: 2.0
Name: awftp
Version: 1.1.0
Summary: awftp - a FTP-style client for HCP Anywhere
Home-page: http://awftp.readthedocs.io/en/latest/
Author: Thorsten Simons
Author-email: sw@snomis.de
License: MIT
Keywords: HCP Anywhere ftp-style client
Platform: UNKNOWN
Classifier: Development Status :: 5 - Production/Stable
Classifier: Intended Audience :: System Administrators
Classifier: Intended Audience :: Other Audience
Classifier: Topic :: Communications :: File Sharing
Classifier: License :: OSI Approved :: MIT License
Classifier: Programming Language :: Python :: 3
Classifier: Operating System :: OS Independent
Classifier: Natural Language :: English
Requires-Dist: beautifulsoup4 (>=4.6.0)
Requires-Dist: click (>=6.7)
Requires-Dist: requests (>=2.13.0)
